MANIFEST.in
README.rst
requirements.txt
setup.cfg
setup.py
kotti_gsd/__init__.py
kotti_gsd/__init__.pyc
kotti_gsd/fanstatic.py
kotti_gsd/fanstatic.pyc
kotti_gsd/resources.pyc
kotti_gsd/util.py
kotti_gsd/util.pyc
kotti_gsd.egg-info/PKG-INFO
kotti_gsd.egg-info/SOURCES.txt
kotti_gsd.egg-info/dependency_links.txt
kotti_gsd.egg-info/entry_points.txt
kotti_gsd.egg-info/not-zip-safe
kotti_gsd.egg-info/requires.txt
kotti_gsd.egg-info/top_level.txt
kotti_gsd/locale/.gitkeep
kotti_gsd/static/scripts.js
kotti_gsd/static/scripts.min.js
kotti_gsd/static/styles.css
kotti_gsd/static/styles.min.css
kotti_gsd/templates/form.pt
kotti_gsd/templates/message.pt
kotti_gsd/templates/service-desk.pt
kotti_gsd/tests/conftest.py
kotti_gsd/tests/test_functional.py
kotti_gsd/tests/test_resources.py
kotti_gsd/tests/test_view.py
kotti_gsd/views/__init__.py
kotti_gsd/views/__init__.pyc
kotti_gsd/views/view.py
kotti_gsd/views/view.pyc