Metadata-Version: 1.1
Name: kotti-gsd
Version: 0.1.0
Summary: Add Gitlab Service Desk to your Kotti site
Home-page: https://github.com/b4oshany/kotti_gsd
Author: Oshane Bailey
Author-email: oshane@alteroo.com
License: BSD-derived (http://www.repoze.org/LICENSE.txt)
Keywords: kotti web cms wcms pylons pyramid sqlalchemy bootstrap gitlab service desk
Platform: UNKNOWN
Classifier: Programming Language :: Python
Classifier: Programming Language :: Python :: 2.7
Classifier: Framework :: Pylons
Classifier: Topic :: Internet :: WWW/HTTP
Classifier: Topic :: Internet :: WWW/HTTP :: Dynamic Content
Classifier: Topic :: Internet :: WWW/HTTP :: WSGI :: Application
Classifier: License :: Repoze Public License
